catsolver/__init__.py
catsolver/forward.py
catsolver/inverse.py
catenary_solver-1.1.0.dist-info/LICENSE.txt
catenary_solver-1.1.0.dist-info/METADATA
catenary_solver-1.1.0.dist-info/WHEEL
catenary_solver-1.1.0.dist-info/top_level.txt
catenary_solver-1.1.0.dist-info/RECORD
