Metadata-Version: 2.1
Name: catenary-solver
Version: 1.1.0
Summary: Python program for finding catenary shapes and mass densities
Author-email: Alan Kwak <alankwak2@gmail.com>
Project-URL: GitHub, https://github.com/alankwak/catenary-solver
Keywords: inverse-problems,catenary
Classifier: License :: OSI Approved :: MIT License
Classifier: Programming Language :: Python
Classifier: Programming Language :: Python :: 3
License-File: LICENSE.txt
Requires-Dist: sympy
Requires-Dist: numpy
Requires-Dist: scipy
